[
  {
    "poolName": "Official Pool",
    "url": "http://pool.raven-dark.com/",
    "searchStrings": [
      "RAbEY5BrCED9p1roAwFZiyckXvd4m4SnsS"
    ]
  },
  {
    "poolName": "Zergpool",
    "url": "https://zergpool.com/",
    "searchStrings": [
      "RWHBWBeihSJwkDGgq7eirnx5zExSv7woBW",
    ]
  },
  {
    "poolName": "mecrypto.club",
    "url": "https://pool.mecrypto.club/",
    "searchStrings": [
      "RNacRrSAqC4uxs68iaLMDmjAznEhSwNn98"
    ]
  },
  {
    "poolName": "pool.crionic.org",
    "url": "https://pool.crionic.org/",
    "searchStrings": [
      "RVbEfZrE3481AydgLjeGMvLWKUXVD8ecLC"
    ]
   }
]
